single_kernel_postgresql/__init__.py
single_kernel_postgresql/abstract_charm.py
single_kernel_postgresql/charmcraft.yaml
single_kernel_postgresql/config/__init__.py
single_kernel_postgresql/config/literals.py
single_kernel_postgresql/utils/__init__.py
single_kernel_postgresql/utils/filesystem.py
single_kernel_postgresql/utils/postgresql.py
postgresql_charms_single_kernel-16.1.6.dist-info/WHEEL
postgresql_charms_single_kernel-16.1.6.dist-info/METADATA
postgresql_charms_single_kernel-16.1.6.dist-info/RECORD
