Metadata-Version: 2.3
Name: postgresql-charms-single-kernel
Version: 16.1.6
Summary: Shared and reusable code for PostgreSQL-related charms
Author: Canonical Data Platform
Author-email: Canonical Data Platform <data-platform@lists.launchpad.net>
License: 
Classifier: Development Status :: 3 - Alpha
Classifier: Intended Audience :: Developers
Classifier: Operating System :: POSIX :: Linux
Requires-Python: >=3.8, <4.0
